python3_midi/__init__.py
python3_midi/constants.py
python3_midi/containers.py
python3_midi/events.py
python3_midi/fileio.py
python3_midi/util.py
python3_midi-0.2.5.data/scripts/mididump.py
python3_midi-0.2.5.data/scripts/mididumphw.py
python3_midi-0.2.5.data/scripts/midiplay.py
python3_midi-0.2.5.dist-info/LICENSE
python3_midi-0.2.5.dist-info/METADATA
python3_midi-0.2.5.dist-info/WHEEL
python3_midi-0.2.5.dist-info/top_level.txt
python3_midi-0.2.5.dist-info/RECORD
