Metadata-Version: 2.1
Name: python3-midi
Version: 0.2.5
Summary: Python MIDI API
Home-page: UNKNOWN
Author: giles hall
Author-email: ghall@csh.rit.edu
License: UNKNOWN
Platform: UNKNOWN
Requires-Python: >=3.5
